vyre/__init__.py
vyre/client.py
vyre_sdk-1.2.0.dist-info/METADATA
vyre_sdk-1.2.0.dist-info/WHEEL
vyre_sdk-1.2.0.dist-info/top_level.txt
vyre_sdk-1.2.0.dist-info/RECORD
