Metadata-Version: 2.4
Name: vyre-sdk
Version: 1.2.0
Summary: Python SDK for Vyre AI Chat API
Home-page: https://github.com/vyre/vyre-python-sdk
Author: Vyre Team
Author-email: support@vyre.com
Project-URL: Documentation, https://docs.vyre.com
Project-URL: Source, https://github.com/vyre/vyre-python-sdk
Project-URL: Tracker, https://github.com/vyre/vyre-python-sdk/issues
Keywords: vyre ai chat sdk api
Classifier: Development Status :: 4 - Beta
Classifier: Intended Audience :: Developers
Classifier: License :: OSI Approved :: MIT License
Classifier: Programming Language :: Python :: 3
Classifier: Programming Language :: Python :: 3.7
Classifier: Programming Language :: Python :: 3.8
Classifier: Programming Language :: Python :: 3.9
Classifier: Programming Language :: Python :: 3.10
Classifier: Programming Language :: Python :: 3.11
Classifier: Topic :: Software Development :: Libraries :: Python Modules
Requires-Python: >=3.7
Requires-Dist: requests>=2.25.0
Requires-Dist: aiohttp>=3.7.0
Dynamic: author
Dynamic: author-email
Dynamic: classifier
Dynamic: description
Dynamic: description-content-type
Dynamic: home-page
Dynamic: keywords
Dynamic: project-url
Dynamic: requires-dist
Dynamic: requires-python
Dynamic: summary
